{
  "formula": "HoAsS",
  "structure": {
    "lattice": [
      [
        4.803277648410555,
        -1e-16,
        2e-16
      ],
      [
        3.2e-15,
        15.442187843059504,
        9e-16
      ],
      [
        0.0,
        -0.0,
        3.7755325731272067
      ]
    ],
    "sites": [
      {
        "species": [
          {
            "element": "Ho",
            "occu": 1.0
          }
        ],
        "xyz": [
          0.029139003853164085,
          5.976286555844903,
          3.4952261364679824e-16
        ]
      },
      {
        "species": [
          {
            "element": "Ho",
            "occu": 1.0
          }
        ],
        "xyz": [
          4.774138644557224,
          9.465901287214379,
          7.504773863531819e-16
        ]
      },
      {
        "species": [
          {
            "element": "Ho",
            "occu": 1.0
          }
        ],
        "xyz": [
          2.430777828058612,
          1.7448073656846288,
          1.8877662865636036
        ]
      },
      {
        "species": [
          {
            "element": "Ho",
            "occu": 1.0
          }
        ],
        "xyz": [
          2.372499820352153,
          13.697380477374876,
          1.8877662865636042
        ]
      },
      {
        "species": [
          {
            "element": "As",
            "occu": 1.0
          }
        ],
        "xyz": [
          2.352606980122532,
          11.435729624044209,
          7.644544156772912e-16
        ]
      },
      {
        "species": [
          {
            "element": "As",
            "occu": 1.0
          }
        ],
        "xyz": [
          2.4506706682880957,
          4.006458219015403,
          3.3554558432271795e-16
        ]
      },
      {
        "species": [
          {
            "element": "As",
            "occu": 1.0
          }
        ],
        "xyz": [
          4.7542458043277405,
          11.727552140545047,
          1.8877662865636042
        ]
      },
      {
        "species": [
          {
            "element": "As",
            "occu": 1.0
          }
        ],
        "xyz": [
          0.04903184408281652,
          3.7146357025141308,
          1.8877662865636036
        ]
      },
      {
        "species": [
          {
            "element": "S",
            "occu": 1.0
          }
        ],
        "xyz": [
          1.2398579512668686,
          7.734922967382686,
          1.8877662865636038
        ]
      },
      {
        "species": [
          {
            "element": "S",
            "occu": 1.0
          }
        ],
        "xyz": [
          3.563419697143656,
          7.707264875677036,
          1.887766286563604
        ]
      },
      {
        "species": [
          {
            "element": "S",
            "occu": 1.0
          }
        ],
        "xyz": [
          3.6414967754721816,
          15.42835879720668,
          1.0508195128145578e-15
        ]
      },
      {
        "species": [
          {
            "element": "S",
            "occu": 1.0
          }
        ],
        "xyz": [
          1.1617808729383765,
          0.01382904585271549,
          4.9180487185436066e-17
        ]
      }
    ]
  },
  "spacegroup": {
    "symbol": "Pnnm",
    "number": 58
  },
  "model_name": "vasp",
  "energy": -74.28920854,
  "fmax": null,
  "e_above_hull": -0.18609266666666713
}