{
  "formula": "HoGe2Pd",
  "structure": {
    "lattice": [
      [
        4.1578464087652325,
        1e-16,
        3e-16
      ],
      [
        3e-15,
        18.8705746202568,
        1.1e-15
      ],
      [
        -0.0,
        0.0,
        4.099975064464777
      ]
    ],
    "sites": [
      {
        "species": [
          {
            "element": "Ho",
            "occu": 1.0
          }
        ],
        "xyz": [
          3.0363419419171857e-16,
          1.9099172395854564,
          3.074981298348583
        ]
      },
      {
        "species": [
          {
            "element": "Ho",
            "occu": 1.0
          }
        ],
        "xyz": [
          2.696365805808281e-15,
          16.960657380671343,
          1.0249937661161952
        ]
      },
      {
        "species": [
          {
            "element": "Ho",
            "occu": 1.0
          }
        ],
        "xyz": [
          2.078923204382618,
          11.345204549713857,
          3.074981298348584
        ]
      },
      {
        "species": [
          {
            "element": "Ho",
            "occu": 1.0
          }
        ],
        "xyz": [
          2.0789232043826176,
          7.525370070542942,
          1.024993766116195
        ]
      },
      {
        "species": [
          {
            "element": "Ge",
            "occu": 1.0
          }
        ],
        "xyz": [
          7.470334185669153e-16,
          4.698983289630836,
          1.0249937661161945
        ]
      },
      {
        "species": [
          {
            "element": "Ge",
            "occu": 1.0
          }
        ],
        "xyz": [
          4.157846408765235,
          14.171591330625963,
          3.0749812983485842
        ]
      },
      {
        "species": [
          {
            "element": "Ge",
            "occu": 1.0
          }
        ],
        "xyz": [
          2.0789232043826185,
          14.134270599759237,
          1.0249937661161952
        ]
      },
      {
        "species": [
          {
            "element": "Ge",
            "occu": 1.0
          }
        ],
        "xyz": [
          2.078923204382617,
          4.736304020497562,
          3.0749812983485834
        ]
      },
      {
        "species": [
          {
            "element": "Ge",
            "occu": 1.0
          }
        ],
        "xyz": [
          1.3869412305924446e-15,
          8.724125995268507,
          3.0749812983485834
        ]
      },
      {
        "species": [
          {
            "element": "Ge",
            "occu": 1.0
          }
        ],
        "xyz": [
          4.157846408765234,
          10.14644862498829,
          1.0249937661161952
        ]
      },
      {
        "species": [
          {
            "element": "Ge",
            "occu": 1.0
          }
        ],
        "xyz": [
          2.0789232043826193,
          18.15941330539691,
          3.0749812983485842
        ]
      },
      {
        "species": [
          {
            "element": "Ge",
            "occu": 1.0
          }
        ],
        "xyz": [
          2.0789232043826162,
          0.7111613148598931,
          1.0249937661161945
        ]
      },
      {
        "species": [
          {
            "element": "Pd",
            "occu": 1.0
          }
        ],
        "xyz": [
          9.979007940769578e-16,
          6.276987132747583,
          3.0749812983485834
        ]
      },
      {
        "species": [
          {
            "element": "Pd",
            "occu": 1.0
          }
        ],
        "xyz": [
          4.157846408765234,
          12.593587487509213,
          1.0249937661161954
        ]
      },
      {
        "species": [
          {
            "element": "Pd",
            "occu": 1.0
          }
        ],
        "xyz": [
          2.078923204382619,
          15.712274442875987,
          3.074981298348584
        ]
      },
      {
        "species": [
          {
            "element": "Pd",
            "occu": 1.0
          }
        ],
        "xyz": [
          2.0789232043826167,
          3.158300177380814,
          1.0249937661161947
        ]
      }
    ]
  },
  "spacegroup": {
    "symbol": "Cmcm",
    "number": 63
  },
  "model_name": "vasp",
  "energy": -94.22643583,
  "fmax": null,
  "e_above_hull": -0.3892492550000002
}