{
  "formula": "KBiS2",
  "structure": {
    "lattice": [
      [
        4.153753411899057,
        1e-16,
        3e-16
      ],
      [
        -2.076876705949528,
        3.597255975760871,
        3e-16
      ],
      [
        0.0,
        -0.0,
        22.371295162737887
      ]
    ],
    "sites": [
      {
        "species": [
          {
            "element": "K",
            "occu": 1.0
          }
        ],
        "xyz": [
          0.0,
          0.0,
          0.0
        ]
      },
      {
        "species": [
          {
            "element": "K",
            "occu": 1.0
          }
        ],
        "xyz": [
          2.076876705949514,
          1.1990853252536322,
          7.457098387579349
        ]
      },
      {
        "species": [
          {
            "element": "K",
            "occu": 1.0
          }
        ],
        "xyz": [
          1.498505427820743e-14,
          2.3981706505072387,
          14.914196775158539
        ]
      },
      {
        "species": [
          {
            "element": "Bi",
            "occu": 1.0
          }
        ],
        "xyz": [
          0.0,
          0.0,
          11.185647581368944
        ]
      },
      {
        "species": [
          {
            "element": "Bi",
            "occu": 1.0
          }
        ],
        "xyz": [
          2.076876705949514,
          1.1990853252536322,
          18.642745968948294
        ]
      },
      {
        "species": [
          {
            "element": "Bi",
            "occu": 1.0
          }
        ],
        "xyz": [
          1.498505427820743e-14,
          2.3981706505072387,
          3.728549193789595
        ]
      },
      {
        "species": [
          {
            "element": "S",
            "occu": 1.0
          }
        ],
        "xyz": [
          0.0,
          0.0,
          5.305075050616087
        ]
      },
      {
        "species": [
          {
            "element": "S",
            "occu": 1.0
          }
        ],
        "xyz": [
          4.153753411899057,
          1e-16,
          17.066220112121798
        ]
      },
      {
        "species": [
          {
            "element": "S",
            "occu": 1.0
          }
        ],
        "xyz": [
          2.076876705949514,
          1.1990853252536322,
          12.762173438195438
        ]
      },
      {
        "species": [
          {
            "element": "S",
            "occu": 1.0
          }
        ],
        "xyz": [
          2.076876705949514,
          1.1990853252536322,
          2.1520233369631034
        ]
      },
      {
        "species": [
          {
            "element": "S",
            "occu": 1.0
          }
        ],
        "xyz": [
          1.498505427820743e-14,
          2.3981706505072387,
          20.219271825774786
        ]
      },
      {
        "species": [
          {
            "element": "S",
            "occu": 1.0
          }
        ],
        "xyz": [
          1.498505427820743e-14,
          2.3981706505072387,
          9.609121724542451
        ]
      }
    ]
  },
  "spacegroup": {
    "symbol": "R-3m",
    "number": 166
  },
  "model_name": "vasp",
  "energy": -49.15834536,
  "fmax": null,
  "e_above_hull": 0.014245622499999833
}