{
  "formula": "NaLiLa2Ti4O12",
  "structure": {
    "lattice": [
      [
        5.511872299322552,
        -0.0,
        3e-16
      ],
      [
        9e-16,
        5.511872299322552,
        3e-16
      ],
      [
        -0.0,
        -0.0,
        7.786693402118373
      ]
    ],
    "sites": [
      {
        "species": [
          {
            "element": "Na",
            "occu": 1.0
          }
        ],
        "xyz": [
          0.0,
          0.0,
          0.0
        ]
      },
      {
        "species": [
          {
            "element": "Li",
            "occu": 1.0
          }
        ],
        "xyz": [
          2.7559361496612764,
          2.755936149661276,
          3.893346701059187
        ]
      },
      {
        "species": [
          {
            "element": "La",
            "occu": 1.0
          }
        ],
        "xyz": [
          0.0,
          0.0,
          3.8933467010591865
        ]
      },
      {
        "species": [
          {
            "element": "La",
            "occu": 1.0
          }
        ],
        "xyz": [
          2.7559361496612764,
          2.755936149661276,
          3e-16
        ]
      },
      {
        "species": [
          {
            "element": "Ti",
            "occu": 1.0
          }
        ],
        "xyz": [
          4.5e-16,
          2.755936149661276,
          1.9524094389386086
        ]
      },
      {
        "species": [
          {
            "element": "Ti",
            "occu": 1.0
          }
        ],
        "xyz": [
          4.5e-16,
          2.755936149661276,
          5.834283963179764
        ]
      },
      {
        "species": [
          {
            "element": "Ti",
            "occu": 1.0
          }
        ],
        "xyz": [
          2.755936149661276,
          0.0,
          1.9524094389386086
        ]
      },
      {
        "species": [
          {
            "element": "Ti",
            "occu": 1.0
          }
        ],
        "xyz": [
          2.755936149661276,
          0.0,
          5.834283963179764
        ]
      },
      {
        "species": [
          {
            "element": "O",
            "occu": 1.0
          }
        ],
        "xyz": [
          1.3794441247880196,
          1.3794441247880194,
          1.954814226364213
        ]
      },
      {
        "species": [
          {
            "element": "O",
            "occu": 1.0
          }
        ],
        "xyz": [
          4.132428174534533,
          4.132428174534532,
          5.831879175754218
        ]
      },
      {
        "species": [
          {
            "element": "O",
            "occu": 1.0
          }
        ],
        "xyz": [
          4.132428174534532,
          1.3794441247880194,
          1.9548142263642132
        ]
      },
      {
        "species": [
          {
            "element": "O",
            "occu": 1.0
          }
        ],
        "xyz": [
          1.37944412478802,
          4.132428174534532,
          5.831879175754218
        ]
      },
      {
        "species": [
          {
            "element": "O",
            "occu": 1.0
          }
        ],
        "xyz": [
          4.132428174534533,
          4.132428174534532,
          1.9548142263642132
        ]
      },
      {
        "species": [
          {
            "element": "O",
            "occu": 1.0
          }
        ],
        "xyz": [
          1.3794441247880196,
          1.3794441247880194,
          5.831879175754218
        ]
      },
      {
        "species": [
          {
            "element": "O",
            "occu": 1.0
          }
        ],
        "xyz": [
          1.37944412478802,
          4.132428174534532,
          1.9548142263642132
        ]
      },
      {
        "species": [
          {
            "element": "O",
            "occu": 1.0
          }
        ],
        "xyz": [
          4.132428174534532,
          1.3794441247880194,
          5.831879175754218
        ]
      },
      {
        "species": [
          {
            "element": "O",
            "occu": 1.0
          }
        ],
        "xyz": [
          4.5e-16,
          2.755936149661276,
          1.5e-16
        ]
      },
      {
        "species": [
          {
            "element": "O",
            "occu": 1.0
          }
        ],
        "xyz": [
          2.755936149661276,
          0.0,
          1.5e-16
        ]
      },
      {
        "species": [
          {
            "element": "O",
            "occu": 1.0
          }
        ],
        "xyz": [
          4.5e-16,
          2.755936149661276,
          3.8933467010591865
        ]
      },
      {
        "species": [
          {
            "element": "O",
            "occu": 1.0
          }
        ],
        "xyz": [
          2.755936149661276,
          0.0,
          3.8933467010591865
        ]
      }
    ]
  },
  "spacegroup": {
    "symbol": "P4/mmm",
    "number": 123
  },
  "model_name": "vasp",
  "energy": -163.43747504,
  "fmax": null,
  "e_above_hull": 0.09783074587497786
}