{
  "formula": "NaVO3",
  "structure": {
    "lattice": [
      [
        5.119836471904035,
        -2.010486356e-07,
        3e-16
      ],
      [
        -2.559918061838791,
        4.433908548415307,
        3e-16
      ],
      [
        0.0,
        0.0,
        15.741377592154375
      ]
    ],
    "sites": [
      {
        "species": [
          {
            "element": "Na",
            "occu": 1.0
          }
        ],
        "xyz": [
          5.119836471904035,
          -2.010486356e-07,
          2.2480774525678364
        ]
      },
      {
        "species": [
          {
            "element": "Na",
            "occu": 1.0
          }
        ],
        "xyz": [
          5.119836471904035,
          -2.010486356e-07,
          13.49330013958654
        ]
      },
      {
        "species": [
          {
            "element": "Na",
            "occu": 1.0
          }
        ],
        "xyz": [
          2.5599182939897416,
          1.4779693821060222,
          7.495203316619218
        ]
      },
      {
        "species": [
          {
            "element": "Na",
            "occu": 1.0
          }
        ],
        "xyz": [
          2.5599182939897416,
          1.4779693821060222,
          2.99904841148366
        ]
      },
      {
        "species": [
          {
            "element": "Na",
            "occu": 1.0
          }
        ],
        "xyz": [
          1.1607550261101111e-07,
          2.955938965260649,
          12.742329180670717
        ]
      },
      {
        "species": [
          {
            "element": "Na",
            "occu": 1.0
          }
        ],
        "xyz": [
          1.1607550261101111e-07,
          2.955938965260649,
          8.246174275535155
        ]
      },
      {
        "species": [
          {
            "element": "V",
            "occu": 1.0
          }
        ],
        "xyz": [
          5.119836471904035,
          -2.010486356e-07,
          5.552897601180124
        ]
      },
      {
        "species": [
          {
            "element": "V",
            "occu": 1.0
          }
        ],
        "xyz": [
          5.119836471904035,
          -2.010486356e-07,
          10.188479990974255
        ]
      },
      {
        "species": [
          {
            "element": "V",
            "occu": 1.0
          }
        ],
        "xyz": [
          2.5599182939897416,
          1.4779693821060222,
          10.800023465231616
        ]
      },
      {
        "species": [
          {
            "element": "V",
            "occu": 1.0
          }
        ],
        "xyz": [
          2.5599182939897416,
          1.4779693821060222,
          15.435605855025639
        ]
      },
      {
        "species": [
          {
            "element": "V",
            "occu": 1.0
          }
        ],
        "xyz": [
          1.1607550261101111e-07,
          2.955938965260649,
          0.30577173712873984
        ]
      },
      {
        "species": [
          {
            "element": "V",
            "occu": 1.0
          }
        ],
        "xyz": [
          1.1607550261101111e-07,
          2.955938965260649,
          4.941354126922756
        ]
      },
      {
        "species": [
          {
            "element": "O",
            "occu": 1.0
          }
        ],
        "xyz": [
          4.125599363484803,
          1.2027604036446544,
          11.588574899853443
        ]
      },
      {
        "species": [
          {
            "element": "O",
            "occu": 1.0
          }
        ],
        "xyz": [
          -1.5656809534195584,
          3.231147943722016,
          4.152802692300929
        ]
      },
      {
        "species": [
          {
            "element": "O",
            "occu": 1.0
          }
        ],
        "xyz": [
          2.0154157259393375,
          2.971493451743788,
          11.588574899853443
        ]
      },
      {
        "species": [
          {
            "element": "O",
            "occu": 1.0
          }
        ],
        "xyz": [
          0.5445026841259059,
          1.4624148956228835,
          4.152802692300929
        ]
      },
      {
        "species": [
          {
            "element": "O",
            "occu": 1.0
          }
        ],
        "xyz": [
          1.5387397925451378,
          0.25965429092959375,
          11.588574899853443
        ]
      },
      {
        "species": [
          {
            "element": "O",
            "occu": 1.0
          }
        ],
        "xyz": [
          1.0211786175201067,
          4.174254056437078,
          4.152802692300929
        ]
      },
      {
        "species": [
          {
            "element": "O",
            "occu": 1.0
          }
        ],
        "xyz": [
          1.5656811855705453,
          2.680729986799313,
          1.0943231717504536
        ]
      },
      {
        "species": [
          {
            "element": "O",
            "occu": 1.0
          }
        ],
        "xyz": [
          3.554155402408992,
          0.2752087774127009,
          9.399928556352428
        ]
      },
      {
        "species": [
          {
            "element": "O",
            "occu": 1.0
          }
        ],
        "xyz": [
          2.015415609863836,
          0.015554486483138641,
          1.0943231717504533
        ]
      },
      {
        "species": [
          {
            "element": "O",
            "occu": 1.0
          }
        ],
        "xyz": [
          3.1044209781156846,
          2.9403842777289055,
          9.399928556352428
        ]
      },
      {
        "species": [
          {
            "element": "O",
            "occu": 1.0
          }
        ],
        "xyz": [
          4.098658086534899,
          1.737623673035584,
          1.0943231717504536
        ]
      },
      {
        "species": [
          {
            "element": "O",
            "occu": 1.0
          }
        ],
        "xyz": [
          1.021178501444603,
          1.2183150911764296,
          9.399928556352428
        ]
      },
      {
        "species": [
          {
            "element": "O",
            "occu": 1.0
          }
        ],
        "xyz": [
          -0.9942369923437473,
          4.158699569953971,
          6.3414490358019515
        ]
      },
      {
        "species": [
          {
            "element": "O",
            "occu": 1.0
          }
        ],
        "xyz": [
          0.9942372244946972,
          1.7531783605673588,
          14.647054420403924
        ]
      },
      {
        "species": [
          {
            "element": "O",
            "occu": 1.0
          }
        ],
        "xyz": [
          -0.5445025680504396,
          1.4935240696377652,
          6.341449035801951
        ]
      },
      {
        "species": [
          {
            "element": "O",
            "occu": 1.0
          }
        ],
        "xyz": [
          0.544502800201409,
          4.418353860883532,
          14.647054420403924
        ]
      },
      {
        "species": [
          {
            "element": "O",
            "occu": 1.0
          }
        ],
        "xyz": [
          1.5387399086206404,
          3.2155932561902425,
          6.3414490358019515
        ]
      },
      {
        "species": [
          {
            "element": "O",
            "occu": 1.0
          }
        ],
        "xyz": [
          -1.5387396764696537,
          2.6962846743310864,
          14.647054420403924
        ]
      }
    ]
  },
  "spacegroup": {
    "symbol": "R-3",
    "number": 148
  },
  "model_name": "vasp",
  "energy": -198.13334908,
  "fmax": null,
  "e_above_hull": 0.07300468166666807
}