{
  "formula": "Gd(Al2Fe)4",
  "structure": {
    "lattice": [
      [
        8.601194386651574,
        0.0,
        -4.953744808995101
      ],
      [
        1.4e-15,
        8.51355743,
        5e-16
      ],
      [
        0.0,
        0.0,
        5.056401
      ]
    ],
    "sites": [
      {
        "species": [
          {
            "element": "Gd",
            "occu": 1.0
          }
        ],
        "xyz": [
          0.0,
          0.0,
          0.0
        ]
      },
      {
        "species": [
          {
            "element": "Gd",
            "occu": 1.0
          }
        ],
        "xyz": [
          4.300597193325788,
          4.256778715,
          -2.47687240449755
        ]
      },
      {
        "species": [
          {
            "element": "Al",
            "occu": 1.0
          }
        ],
        "xyz": [
          3.291735999999986e-16,
          2.0017416771713115,
          2.5282005
        ]
      },
      {
        "species": [
          {
            "element": "Al",
            "occu": 1.0
          }
        ],
        "xyz": [
          1.0708264000000015e-15,
          6.511815752828689,
          2.5282005000000005
        ]
      },
      {
        "species": [
          {
            "element": "Al",
            "occu": 1.0
          }
        ],
        "xyz": [
          4.300597193325788,
          6.258520392171312,
          0.05132809550245021
        ]
      },
      {
        "species": [
          {
            "element": "Al",
            "occu": 1.0
          }
        ],
        "xyz": [
          4.300597193325787,
          2.255037037828689,
          0.051328095502449766
        ]
      },
      {
        "species": [
          {
            "element": "Al",
            "occu": 1.0
          }
        ],
        "xyz": [
          4.798892000000038e-16,
          2.9182601887405633,
          1.7138900000000135e-16
        ]
      },
      {
        "species": [
          {
            "element": "Al",
            "occu": 1.0
          }
        ],
        "xyz": [
          9.201107999999962e-16,
          5.595297241259438,
          3.2861099999999867e-16
        ]
      },
      {
        "species": [
          {
            "element": "Al",
            "occu": 1.0
          }
        ],
        "xyz": [
          4.300597193325788,
          7.175038903740563,
          -2.47687240449755
        ]
      },
      {
        "species": [
          {
            "element": "Al",
            "occu": 1.0
          }
        ],
        "xyz": [
          4.300597193325787,
          1.3385185262594372,
          -2.4768724044975503
        ]
      },
      {
        "species": [
          {
            "element": "Al",
            "occu": 1.0
          }
        ],
        "xyz": [
          1.3522969838581114,
          4.256778715,
          2.5443403116621726
        ]
      },
      {
        "species": [
          {
            "element": "Al",
            "occu": 1.0
          }
        ],
        "xyz": [
          7.248897402793465,
          4.256778715,
          -2.441684120657272
        ]
      },
      {
        "species": [
          {
            "element": "Al",
            "occu": 1.0
          }
        ],
        "xyz": [
          5.652894177183898,
          0.0,
          0.06746790716462196
        ]
      },
      {
        "species": [
          {
            "element": "Al",
            "occu": 1.0
          }
        ],
        "xyz": [
          2.9483002094676767,
          0.0,
          0.03518828384027779
        ]
      },
      {
        "species": [
          {
            "element": "Al",
            "occu": 1.0
          }
        ],
        "xyz": [
          2.0223472289670563,
          0.0,
          2.552337434253836
        ]
      },
      {
        "species": [
          {
            "element": "Al",
            "occu": 1.0
          }
        ],
        "xyz": [
          6.578847157684518,
          0.0,
          -2.4496812432489365
        ]
      },
      {
        "species": [
          {
            "element": "Al",
            "occu": 1.0
          }
        ],
        "xyz": [
          6.322944422292844,
          4.256778715,
          0.07546502975628604
        ]
      },
      {
        "species": [
          {
            "element": "Al",
            "occu": 1.0
          }
        ],
        "xyz": [
          2.2782499643587317,
          4.256778715,
          0.027191161248614155
        ]
      },
      {
        "species": [
          {
            "element": "Fe",
            "occu": 1.0
          }
        ],
        "xyz": [
          2.150298596662894,
          2.1283893575,
          -1.238436202248775
        ]
      },
      {
        "species": [
          {
            "element": "Fe",
            "occu": 1.0
          }
        ],
        "xyz": [
          6.450895789988682,
          6.385168072500001,
          -3.715308606746325
        ]
      },
      {
        "species": [
          {
            "element": "Fe",
            "occu": 1.0
          }
        ],
        "xyz": [
          6.450895789988681,
          2.1283893575,
          -3.7153086067463255
        ]
      },
      {
        "species": [
          {
            "element": "Fe",
            "occu": 1.0
          }
        ],
        "xyz": [
          2.1502985966628945,
          6.385168072500001,
          -1.2384362022487747
        ]
      },
      {
        "species": [
          {
            "element": "Fe",
            "occu": 1.0
          }
        ],
        "xyz": [
          2.150298596662894,
          2.1283893575,
          1.2897642977512251
        ]
      },
      {
        "species": [
          {
            "element": "Fe",
            "occu": 1.0
          }
        ],
        "xyz": [
          6.450895789988682,
          6.385168072500001,
          -1.187108106746325
        ]
      },
      {
        "species": [
          {
            "element": "Fe",
            "occu": 1.0
          }
        ],
        "xyz": [
          6.450895789988681,
          2.1283893575,
          -1.1871081067463254
        ]
      },
      {
        "species": [
          {
            "element": "Fe",
            "occu": 1.0
          }
        ],
        "xyz": [
          2.1502985966628945,
          6.385168072500001,
          1.2897642977512254
        ]
      }
    ]
  },
  "spacegroup": {
    "symbol": "C2/m",
    "number": 12
  },
  "model_name": "vasp",
  "energy": -159.82032323,
  "fmax": null,
  "e_above_hull": 0.22658539884615259
}