{
  "formula": "Gd(Al2Fe)4",
  "structure": {
    "lattice": [
      [
        8.64966964,
        0.0,
        5e-16
      ],
      [
        1.4e-15,
        8.64966964,
        5e-16
      ],
      [
        0.0,
        0.0,
        4.97280594
      ]
    ],
    "sites": [
      {
        "species": [
          {
            "element": "Gd",
            "occu": 1.0
          }
        ],
        "xyz": [
          0.0,
          0.0,
          0.0
        ]
      },
      {
        "species": [
          {
            "element": "Gd",
            "occu": 1.0
          }
        ],
        "xyz": [
          4.324834820000001,
          4.32483482,
          2.4864029700000003
        ]
      },
      {
        "species": [
          {
            "element": "Al",
            "occu": 1.0
          }
        ],
        "xyz": [
          4.774422519999959e-16,
          2.94979839426971,
          1.7051508999999855e-16
        ]
      },
      {
        "species": [
          {
            "element": "Al",
            "occu": 1.0
          }
        ],
        "xyz": [
          9.22557748000004e-16,
          5.69987124573029,
          3.2948491000000146e-16
        ]
      },
      {
        "species": [
          {
            "element": "Al",
            "occu": 1.0
          }
        ],
        "xyz": [
          5.69987124573029,
          0.0,
          3.2948491000000146e-16
        ]
      },
      {
        "species": [
          {
            "element": "Al",
            "occu": 1.0
          }
        ],
        "xyz": [
          2.94979839426971,
          0.0,
          1.7051508999999855e-16
        ]
      },
      {
        "species": [
          {
            "element": "Al",
            "occu": 1.0
          }
        ],
        "xyz": [
          4.324834820000001,
          7.274633214269711,
          2.4864029700000008
        ]
      },
      {
        "species": [
          {
            "element": "Al",
            "occu": 1.0
          }
        ],
        "xyz": [
          4.32483482,
          1.37503642573029,
          2.4864029700000003
        ]
      },
      {
        "species": [
          {
            "element": "Al",
            "occu": 1.0
          }
        ],
        "xyz": [
          1.3750364257302907,
          4.32483482,
          2.4864029700000003
        ]
      },
      {
        "species": [
          {
            "element": "Al",
            "occu": 1.0
          }
        ],
        "xyz": [
          7.274633214269712,
          4.32483482,
          2.4864029700000008
        ]
      },
      {
        "species": [
          {
            "element": "Al",
            "occu": 1.0
          }
        ],
        "xyz": [
          4.774422519999959e-16,
          2.94979839426971,
          2.48640297
        ]
      },
      {
        "species": [
          {
            "element": "Al",
            "occu": 1.0
          }
        ],
        "xyz": [
          9.22557748000004e-16,
          5.69987124573029,
          2.4864029700000003
        ]
      },
      {
        "species": [
          {
            "element": "Al",
            "occu": 1.0
          }
        ],
        "xyz": [
          5.69987124573029,
          0.0,
          2.4864029700000003
        ]
      },
      {
        "species": [
          {
            "element": "Al",
            "occu": 1.0
          }
        ],
        "xyz": [
          2.94979839426971,
          0.0,
          2.48640297
        ]
      },
      {
        "species": [
          {
            "element": "Al",
            "occu": 1.0
          }
        ],
        "xyz": [
          4.324834820000001,
          7.274633214269711,
          6.705150899999986e-16
        ]
      },
      {
        "species": [
          {
            "element": "Al",
            "occu": 1.0
          }
        ],
        "xyz": [
          4.32483482,
          1.37503642573029,
          3.2948491000000146e-16
        ]
      },
      {
        "species": [
          {
            "element": "Al",
            "occu": 1.0
          }
        ],
        "xyz": [
          1.3750364257302907,
          4.32483482,
          3.2948491000000146e-16
        ]
      },
      {
        "species": [
          {
            "element": "Al",
            "occu": 1.0
          }
        ],
        "xyz": [
          7.274633214269712,
          4.32483482,
          6.705150899999986e-16
        ]
      },
      {
        "species": [
          {
            "element": "Fe",
            "occu": 1.0
          }
        ],
        "xyz": [
          2.1624174100000007,
          2.16241741,
          1.2432014850000002
        ]
      },
      {
        "species": [
          {
            "element": "Fe",
            "occu": 1.0
          }
        ],
        "xyz": [
          6.487252230000002,
          6.487252230000001,
          3.7296044550000005
        ]
      },
      {
        "species": [
          {
            "element": "Fe",
            "occu": 1.0
          }
        ],
        "xyz": [
          6.487252230000001,
          2.16241741,
          1.2432014850000004
        ]
      },
      {
        "species": [
          {
            "element": "Fe",
            "occu": 1.0
          }
        ],
        "xyz": [
          2.162417410000001,
          6.487252230000001,
          3.7296044550000005
        ]
      },
      {
        "species": [
          {
            "element": "Fe",
            "occu": 1.0
          }
        ],
        "xyz": [
          6.487252230000002,
          6.487252230000001,
          1.2432014850000006
        ]
      },
      {
        "species": [
          {
            "element": "Fe",
            "occu": 1.0
          }
        ],
        "xyz": [
          2.1624174100000007,
          2.16241741,
          3.729604455
        ]
      },
      {
        "species": [
          {
            "element": "Fe",
            "occu": 1.0
          }
        ],
        "xyz": [
          2.162417410000001,
          6.487252230000001,
          1.2432014850000004
        ]
      },
      {
        "species": [
          {
            "element": "Fe",
            "occu": 1.0
          }
        ],
        "xyz": [
          6.487252230000001,
          2.16241741,
          3.7296044550000005
        ]
      }
    ]
  },
  "spacegroup": {
    "symbol": "I4/mmm",
    "number": 139
  },
  "model_name": "vasp",
  "energy": -115.48268437,
  "fmax": null,
  "e_above_hull": 1.931879201153846
}