{
  "formula": "GdCBr",
  "structure": {
    "lattice": [
      [
        3.89171646,
        0.0,
        2e-16
      ],
      [
        6e-16,
        3.89171646,
        2e-16
      ],
      [
        0.0,
        0.0,
        7.97478364
      ]
    ],
    "sites": [
      {
        "species": [
          {
            "element": "Gd",
            "occu": 1.0
          }
        ],
        "xyz": [
          3e-16,
          1.94585823,
          5.774983912703037
        ]
      },
      {
        "species": [
          {
            "element": "Gd",
            "occu": 1.0
          }
        ],
        "xyz": [
          1.94585823,
          0.0,
          2.199799727296963
        ]
      },
      {
        "species": [
          {
            "element": "C",
            "occu": 1.0
          }
        ],
        "xyz": [
          0.0,
          0.0,
          0.0
        ]
      },
      {
        "species": [
          {
            "element": "C",
            "occu": 1.0
          }
        ],
        "xyz": [
          1.9458582300000002,
          1.94585823,
          2e-16
        ]
      },
      {
        "species": [
          {
            "element": "Br",
            "occu": 1.0
          }
        ],
        "xyz": [
          3e-16,
          1.94585823,
          2.96528892142967
        ]
      },
      {
        "species": [
          {
            "element": "Br",
            "occu": 1.0
          }
        ],
        "xyz": [
          1.94585823,
          0.0,
          5.0094947185703305
        ]
      }
    ]
  },
  "spacegroup": {
    "symbol": "P4/nmm",
    "number": 129
  },
  "model_name": "vasp",
  "energy": -42.76046371,
  "fmax": null,
  "e_above_hull": 2.2883135533333325
}