{
  "formula": "SnSe",
  "structure": {
    "lattice": [
      [
        3.9102445660435716,
        0.0,
        -1.3002346683321966
      ],
      [
        7e-16,
        4.30477435,
        3e-16
      ],
      [
        0.0,
        0.0,
        6.26154236
      ]
    ],
    "sites": [
      {
        "species": [
          {
            "element": "Sn",
            "occu": 1.0
          }
        ],
        "xyz": [
          1.5166133805052102,
          3.2285807625,
          4.352854156164269
        ]
      },
      {
        "species": [
          {
            "element": "Sn",
            "occu": 1.0
          }
        ],
        "xyz": [
          2.393631185538362,
          1.0761935875,
          0.6084535355035348
        ]
      },
      {
        "species": [
          {
            "element": "Se",
            "occu": 1.0
          }
        ],
        "xyz": [
          0.5297873837244345,
          3.2285807625,
          1.5205505094073097
        ]
      },
      {
        "species": [
          {
            "element": "Se",
            "occu": 1.0
          }
        ],
        "xyz": [
          3.3804571823191374,
          1.0761935875,
          3.440757182260494
        ]
      }
    ]
  },
  "spacegroup": {
    "symbol": "P2_1/m",
    "number": 11
  },
  "model_name": "vasp",
  "energy": -16.17073817,
  "fmax": null,
  "e_above_hull": 0.14260719124999977
}